oilspillsim.cpython-39-x86_64-linux-gnu.so
oilspillsim.libs/libgcc_s-0cd532bd.so.1
oilspillsim.libs/libstdc++-5d72f927.so.6.0.33
oilspillsim-0.0.2.dist-info/METADATA
oilspillsim-0.0.2.dist-info/WHEEL
oilspillsim-0.0.2.dist-info/top_level.txt
oilspillsim-0.0.2.dist-info/RECORD
oilspillsim-0.0.2.dist-info/licenses/LICENSE
