Metadata-Version: 2.1
Name: oilspillsim
Version: 0.0.2
Summary: First package version of Oil Spill simulator
Home-page: https://github.com/AloePacci/cpp_oil_simulator
Author: Alejandro Casado Pérez
Author-email: acasado4@us.es
License-File: LICENSE
Requires-Dist: numpy
Provides-Extra: test
Requires-Dist: pytest ; extra == 'test'
